Orange3_Text-1.16.3-py3.11-nspkg.pth
orange3_text-1.16.3.data/data/help/orange3-text/.buildinfo
orange3_text-1.16.3.data/data/help/orange3-text/genindex.html
orange3_text-1.16.3.data/data/help/orange3-text/index.html
orange3_text-1.16.3.data/data/help/orange3-text/objects.inv
orange3_text-1.16.3.data/data/help/orange3-text/py-modindex.html
orange3_text-1.16.3.data/data/help/orange3-text/search.html
orange3_text-1.16.3.data/data/help/orange3-text/searchindex.js
orange3_text-1.16.3.data/data/help/orange3-text/_images/Annotator-Example.png
orange3_text-1.16.3.data/data/help/orange3-text/_images/Annotator.png
orange3_text-1.16.3.data/data/help/orange3-text/_images/Bag-of-Words-Example1.png
orange3_text-1.16.3.data/data/help/orange3-text/_images/Bag-of-Words-Example2.png
orange3_text-1.16.3.data/data/help/orange3-text/_images/Bag-of-Words-stamped.png
orange3_text-1.16.3.data/data/help/orange3-text/_images/Collocations-Example.png
orange3_text-1.16.3.data/data/help/orange3-text/_images/Collocations.png
orange3_text-1.16.3.data/data/help/orange3-text/_images/Concordance-Example1.png
orange3_text-1.16.3.data/data/help/orange3-text/_images/Concordance-Example2.png
orange3_text-1.16.3.data/data/help/orange3-text/_images/Concordance-stamped.png
orange3_text-1.16.3.data/data/help/orange3-text/_images/Corpus-Example1.png
orange3_text-1.16.3.data/data/help/orange3-text/_images/Corpus-Example2.png
orange3_text-1.16.3.data/data/help/orange3-text/_images/Corpus-Viewer-Example.png
orange3_text-1.16.3.data/data/help/orange3-text/_images/Corpus-Viewer-stamped.png
orange3_text-1.16.3.data/data/help/orange3-text/_images/Corpus-stamped.png
orange3_text-1.16.3.data/data/help/orange3-text/_images/Corpus-to-Network-Example1.png
orange3_text-1.16.3.data/data/help/orange3-text/_images/Corpus-to-Network-Example2.png
orange3_text-1.16.3.data/data/help/orange3-text/_images/Corpus-to-Network-Example3.png
orange3_text-1.16.3.data/data/help/orange3-text/_images/Corpus-to-Network-stamped.png
orange3_text-1.16.3.dist-info/licenses/LICENSE
orange3_text-1.16.3.dist-info/METADATA
orange3_text-1.16.3.dist-info/WHEEL
orange3_text-1.16.3.dist-info/entry_points.txt
orange3_text-1.16.3.dist-info/namespace_packages.txt
orange3_text-1.16.3.dist-info/top_level.txt
orange3_text-1.16.3.dist-info/RECORD
